dslmodel/__init__.py
dslmodel/agent_model.py
dslmodel/api.py
dslmodel/apis/__init__.py
dslmodel/apis/auto_router.py
dslmodel/apis/auto_signature_route.py
dslmodel/cli.py
dslmodel/clis/__init__.py
dslmodel/clis/auto_command.py
dslmodel/clis/auto_model_command.py
dslmodel/clis/gen_cmd_func.py
dslmodel/clis/generate_zod.py
dslmodel/commands/__init__.py
dslmodel/commands/asyncapi.py
dslmodel/commands/slidev.py
dslmodel/commands/slidev_utils.py
dslmodel/conditional_cors_middleware.py
dslmodel/config.toml
dslmodel/dataset.py
dslmodel/dsl_models.py
dslmodel/dspy_modules/__init__.py
dslmodel/dspy_modules/file_name_module.py
dslmodel/dspy_modules/fsm_trigger_module.py
dslmodel/dspy_modules/gen_pydantic_instance.py
dslmodel/dspy_modules/tool_trigger_module.py
dslmodel/events/__init__.py
dslmodel/events/example_event.py
dslmodel/examples/__init__.py
dslmodel/examples/aps_models.py
dslmodel/examples/career/__init__.py
dslmodel/examples/career/job_models.py
dslmodel/examples/chat_completions.ipynb
dslmodel/examples/class_generation.ipynb
dslmodel/examples/classes/__init__.py
dslmodel/examples/components/HelloWorld.vue
dslmodel/examples/demo.py
dslmodel/examples/domain_gen.py
dslmodel/examples/domains.ipynb
dslmodel/examples/domains.yaml
dslmodel/examples/dsls/__init__.py
dslmodel/examples/dsls/ipynb_dsl.py
dslmodel/examples/dspy.ipynb
dslmodel/examples/example_notebook.ipynb
dslmodel/examples/framework/__init__.py
dslmodel/examples/framework/agent-api-spec.md
dslmodel/examples/framework/agile-protocol-spec.ipynb
dslmodel/examples/framework/camunda_house_bpmn_models.py
dslmodel/examples/framework/code_blueprint.py
dslmodel/examples/framework/code_context_models.py
dslmodel/examples/framework/from_prompt_chain.ipynb
dslmodel/examples/framework/sas_bpmn.py
dslmodel/examples/framework/scrum_at_scale_models.py
dslmodel/examples/gh/__init__.py
dslmodel/examples/gh/github.ipynb
dslmodel/examples/gh_actions_models.py
dslmodel/examples/gherkin_models.py
dslmodel-2024.12.22.2.dist-info/METADATA
dslmodel-2024.12.22.2.dist-info/WHEEL
dslmodel-2024.12.22.2.dist-info/entry_points.txt
dslmodel-2024.12.22.2.dist-info/RECORD
