Metadata-Version: 2.1
Name: dslmodel
Version: 2024.12.22.2
Summary: Pydantic + DSPy instances from prompts and Jinja.
Home-page: https://github.com/seanchatmangpt/dslmodel
Author: Sean Chatman
Author-email: info@chatmangpt.com
Requires-Python: >=3.12,<4.0
Classifier: Programming Language :: Python :: 3
Classifier: Programming Language :: Python :: 3.12
Classifier: Programming Language :: Python :: 3.13
Requires-Dist: aiofiles (>=24.1.0,<25.0.0)
Requires-Dist: apscheduler (>=3.10.4,<4.0.0)
Requires-Dist: cloudpickle (>=3.1.0,<4.0.0)
Requires-Dist: coloredlogs (>=15.0.1)
Requires-Dist: dspy-ai (>=2.5.6,<3.0.0)
Requires-Dist: factory-boy (>=3.3.1,<4.0.0)
Requires-Dist: hypothesis (>=6.114.1,<7.0.0)
Requires-Dist: ijson (>=3.3.0,<4.0.0)
Requires-Dist: inflection (>=0.5.1,<0.6.0)
Requires-Dist: inject (>=5.2.1,<6.0.0)
Requires-Dist: injector (>=0.22.0,<0.23.0)
Requires-Dist: jinja2-ext (>=0.1,<0.2)
Requires-Dist: jinja2-time (>=0.2.0,<0.3.0)
Requires-Dist: jupyter (>=1.1.1,<2.0.0)
Requires-Dist: loguru (>=0.7.2,<0.8.0)
Requires-Dist: mcp (>=1.0.0,<2.0.0)
Requires-Dist: munch (>=4.0.0,<5.0.0)
Requires-Dist: nest-asyncio (>=1.6.0,<2.0.0)
Requires-Dist: pandasql (>=0.7.3,<0.8.0)
Requires-Dist: poethepoet (>=0.25.0)
Requires-Dist: pydantic-ai (>=0.0.14,<0.0.15)
Requires-Dist: pygithub (>=2.4.0,<3.0.0)
Requires-Dist: pyperclip (>=1.9.0,<2.0.0)
Requires-Dist: pytest (>=8.3.3,<9.0.0)
Requires-Dist: pytest-xdist (>=3.6.1,<4.0.0)
Requires-Dist: python-socketio[asyncio-client] (>=5.11.4,<6.0.0)
Requires-Dist: reactivex (>=4.0.4,<5.0.0)
Requires-Dist: toml (>=0.10.2,<0.11.0)
Requires-Dist: transitions (>=0.9.2,<0.10.0)
Requires-Dist: wcmatch (>=10.0,<11.0)
Project-URL: Repository, https://github.com/seanchatmangpt/dslmodel
